odoo/addons/l10n_fr_chorus_account/README.rst
odoo/addons/l10n_fr_chorus_account/__init__.py
odoo/addons/l10n_fr_chorus_account/__manifest__.py
odoo/addons/l10n_fr_chorus_account/data/cron.xml
odoo/addons/l10n_fr_chorus_account/data/mail_template.xml
odoo/addons/l10n_fr_chorus_account/data/transmit_method.xml
odoo/addons/l10n_fr_chorus_account/demo/demo.xml
odoo/addons/l10n_fr_chorus_account/i18n/am.po
odoo/addons/l10n_fr_chorus_account/i18n/bg.po
odoo/addons/l10n_fr_chorus_account/i18n/ca.po
odoo/addons/l10n_fr_chorus_account/i18n/da.po
odoo/addons/l10n_fr_chorus_account/i18n/de.po
odoo/addons/l10n_fr_chorus_account/i18n/el_GR.po
odoo/addons/l10n_fr_chorus_account/i18n/es.po
odoo/addons/l10n_fr_chorus_account/i18n/es_ES.po
odoo/addons/l10n_fr_chorus_account/i18n/es_MX.po
odoo/addons/l10n_fr_chorus_account/i18n/fi.po
odoo/addons/l10n_fr_chorus_account/i18n/fr.po
odoo/addons/l10n_fr_chorus_account/i18n/fr_CH.po
odoo/addons/l10n_fr_chorus_account/i18n/gl.po
odoo/addons/l10n_fr_chorus_account/i18n/hr.po
odoo/addons/l10n_fr_chorus_account/i18n/it.po
odoo/addons/l10n_fr_chorus_account/i18n/l10n_fr_chorus_account.pot
odoo/addons/l10n_fr_chorus_account/i18n/nb_NO.po
odoo/addons/l10n_fr_chorus_account/i18n/nl.po
odoo/addons/l10n_fr_chorus_account/i18n/pt.po
odoo/addons/l10n_fr_chorus_account/i18n/pt_BR.po
odoo/addons/l10n_fr_chorus_account/i18n/pt_PT.po
odoo/addons/l10n_fr_chorus_account/i18n/sl.po
odoo/addons/l10n_fr_chorus_account/i18n/tr.po
odoo/addons/l10n_fr_chorus_account/models/__init__.py
odoo/addons/l10n_fr_chorus_account/models/account_invoice.py
odoo/addons/l10n_fr_chorus_account/models/chorus_flow.py
odoo/addons/l10n_fr_chorus_account/models/chorus_partner_service.py
odoo/addons/l10n_fr_chorus_account/models/company.py
odoo/addons/l10n_fr_chorus_account/models/config_settings.py
odoo/addons/l10n_fr_chorus_account/models/partner.py
odoo/addons/l10n_fr_chorus_account/readme/CONFIGURE.rst
odoo/addons/l10n_fr_chorus_account/readme/CONTRIBUTORS.rst
odoo12_addon_l10n_fr_chorus_account-12.0.1.2.0.dist-info/METADATA
odoo12_addon_l10n_fr_chorus_account-12.0.1.2.0.dist-info/WHEEL
odoo12_addon_l10n_fr_chorus_account-12.0.1.2.0.dist-info/top_level.txt
odoo12_addon_l10n_fr_chorus_account-12.0.1.2.0.dist-info/RECORD
