Metadata-Version: 2.1
Name: odoo12-addon-l10n-fr-chorus-account
Version: 12.0.1.2.0
Summary: Generate Chorus-compliant e-invoices and transmit them via the Chorus API
Home-page: https://github.com/OCA/l10n-france
Author: Akretion,Odoo Community Association (OCA)
Author-email: support@odoo-community.org
License: AGPL-3
Platform: UNKNOWN
Classifier: Programming Language :: Python
Classifier: Framework :: Odoo
Classifier: Framework :: Odoo :: 12.0
Classifier: License :: OSI Approved :: GNU Affero General Public License v3
Requires-Python: >=3.5
Requires-Dist: odoo12-addon-account-invoice-transmit-method
Requires-Dist: odoo12-addon-agreement-account
Requires-Dist: odoo12-addon-l10n-fr-siret
Requires-Dist: odoo12-addon-server-environment
Requires-Dist: odoo <12.1dev,>=12.0a
Requires-Dist: requests-oauthlib
